MANIFEST.in
README
setup.py
test/__init__.py
test/client.py
test/top.py
test/torrent.py
test/utils.py
test/data/add.json
test/data/add_torrent_base64.json
test/data/adduri.json
test/data/addurl.json
test/data/construction.json
test/data/get_torrent.json
test/data/get_torrent_hash.json
test/data/get_torrents_2to3.json
test/data/get_torrents_hashes.json
test/data/info.json
test/data/remove.json
test/data/start.json
test/data/stop.json
test/data/torrent.txt
test/data/verify.json
transmissionrpc/__init__.py
transmissionrpc/client.py
transmissionrpc/constants.py
transmissionrpc/error.py
transmissionrpc/httphandler.py
transmissionrpc/session.py
transmissionrpc/torrent.py
transmissionrpc/utils.py
transmissionrpc.egg-info/PKG-INFO
transmissionrpc.egg-info/SOURCES.txt
transmissionrpc.egg-info/dependency_links.txt
transmissionrpc.egg-info/requires.txt
transmissionrpc.egg-info/top_level.txt
transmissionrpc.egg-info/zip-safe