Metadata-Version: 1.1
Name: transmissionrpc
Version: 0.10
Summary: Python module that implements the Transmission bittorent client RPC protocol.
Home-page: http://bitbucket.org/blueluna/transmissionrpc
Author: Erik Svensson
Author-email: erik.public@gmail.com
License: UNKNOWN
Keywords: transmission bittorent torrent
Platform: UNKNOWN
Classifier: Intended Audience :: Developers
Classifier: License :: OSI Approved :: MIT License
Classifier: Topic :: Communications :: File Sharing
Classifier: Topic :: Internet
